georelate/__init__.py
georelate/_distance.py
georelate/data.py
georelate-0.0.3.dist-info/LICENSE
georelate-0.0.3.dist-info/METADATA
georelate-0.0.3.dist-info/WHEEL
georelate-0.0.3.dist-info/RECORD
