Metadata-Version: 2.1
Name: georelate
Version: 0.0.3
Summary: Georelate constructs design matrices from geographical data.
Author: edkrueger
Author-email: edkrueger@gmail.com
Requires-Python: >=3.10,<4.0
Classifier: Programming Language :: Python :: 3
Classifier: Programming Language :: Python :: 3.10
Classifier: Programming Language :: Python :: 3.11
Requires-Dist: numpy (>=1.24.3,<2.0.0)
Requires-Dist: pandas (>=2.0.1,<3.0.0)
